nonebot_plugin_pcr_sign-0.3.2.dist-info/METADATA
nonebot_plugin_pcr_sign-0.3.2.dist-info/WHEEL
nonebot_plugin_pcr_sign-0.3.2.dist-info/entry_points.txt
nonebot_plugin_pcr_sign-0.3.2.dist-info/licenses/LICENSE
nonebot_plugin_pcr_sign/__init__.py
nonebot_plugin_pcr_sign/cli/__init__.py
nonebot_plugin_pcr_sign/cli/__main__.py
nonebot_plugin_pcr_sign/cli/plugins/__init__.py
nonebot_plugin_pcr_sign/cli/plugins/migrate.py
nonebot_plugin_pcr_sign/config.py
nonebot_plugin_pcr_sign/db_handler.py
nonebot_plugin_pcr_sign/migrations/94353282a8c6_first_revision.py
nonebot_plugin_pcr_sign/models.py
nonebot_plugin_pcr_sign/render.py
nonebot_plugin_pcr_sign/resources/fonts/MaokenZhuyuanTi.ttf
nonebot_plugin_pcr_sign/resources/images/album_background/card.png
nonebot_plugin_pcr_sign/resources/images/album_background/frame.png
nonebot_plugin_pcr_sign/resources/images/album_background/kraft_page.png
nonebot_plugin_pcr_sign/resources/images/album_background/pcr_frame.png
nonebot_plugin_pcr_sign/resources/images/background.png
nonebot_plugin_pcr_sign/resources/images/new.png
nonebot_plugin_pcr_sign/resources/images/sign_background/background.png
nonebot_plugin_pcr_sign/resources/images/sign_background/custom_bg_1.jpg
nonebot_plugin_pcr_sign/resources/images/sign_background/custom_bg_2.png
nonebot_plugin_pcr_sign/resources/images/sign_background/custom_bg_3.jpg
nonebot_plugin_pcr_sign/resources/images/sign_background/custom_bg_4.jpg
nonebot_plugin_pcr_sign/resources/stamps/1.png
nonebot_plugin_pcr_sign/resources/stamps/10.png
nonebot_plugin_pcr_sign/resources/stamps/100.png
nonebot_plugin_pcr_sign/resources/stamps/101.png
nonebot_plugin_pcr_sign/resources/stamps/102.png
nonebot_plugin_pcr_sign/resources/stamps/103.png
nonebot_plugin_pcr_sign/resources/stamps/104.png
nonebot_plugin_pcr_sign/resources/stamps/105.png
nonebot_plugin_pcr_sign/resources/stamps/106.png
nonebot_plugin_pcr_sign/resources/stamps/107.png
nonebot_plugin_pcr_sign/resources/stamps/108.png
nonebot_plugin_pcr_sign/resources/stamps/109.png
nonebot_plugin_pcr_sign/resources/stamps/11.png
nonebot_plugin_pcr_sign/resources/stamps/110.png
nonebot_plugin_pcr_sign/resources/stamps/111.png
nonebot_plugin_pcr_sign-0.3.2.dist-info/RECORD
