Metadata-Version: 2.1
Name: nonebot-plugin-pcr-sign
Version: 0.3.2
Summary: nonebot_plugin_hoshino_sign 的重置版
Author-Email: FrostN0v0  <1614591760@qq.com>
Project-URL: homepage, https://github.com/FrostN0v0/nonebot-plugin-pcr-sign
Project-URL: repository, https://github.com/FrostN0v0/nonebot-plugin-pcr-sign
Requires-Python: >=3.10
Requires-Dist: httpx>=0.27.2
Requires-Dist: nonebot-plugin-alconna>=0.53.1
Requires-Dist: nonebot-plugin-argot>=0.1.8
Requires-Dist: nonebot-plugin-htmlrender>=0.4.0
Requires-Dist: nonebot-plugin-localstore>=0.7.2
Requires-Dist: nonebot-plugin-orm>=0.7.6
Requires-Dist: nonebot-plugin-uninfo>=0.4.1
Requires-Dist: nonebot2>=2.4.1
Provides-Extra: adapters
Requires-Dist: nonebot-adapter-onebot>=2.4.6; extra == "adapters"
Requires-Dist: nonebot-adapter-telegram>=0.1.0b20; extra == "adapters"
Provides-Extra: test
Requires-Dist: nonebot2[fastapi,httpx]>=2.4.0; extra == "test"
Requires-Dist: nonebot-plugin-orm[default]>=0.7.6; extra == "test"
Provides-Extra: cli
Requires-Dist: aiosqlite>=0.20.0; extra == "cli"
Requires-Dist: cli-lite>=0.10.2; extra == "cli"
